lib_for_messanger
